promptsite/__init__.py
promptsite/cli.py
promptsite/config.py
promptsite/core.py
promptsite/decorator.py
promptsite/exceptions.py
promptsite/llm.py
promptsite/model/__init__.py
promptsite/model/dataset.py
promptsite/model/prompt.py
promptsite/model/run.py
promptsite/model/variable.py
promptsite/model/version.py
promptsite/query.py
promptsite/storage/__init__.py
promptsite/storage/base.py
promptsite/storage/file.py
promptsite/storage/git.py
promptsite-0.4.0.dist-info/LICENSE
promptsite-0.4.0.dist-info/METADATA
promptsite-0.4.0.dist-info/WHEEL
promptsite-0.4.0.dist-info/entry_points.txt
promptsite-0.4.0.dist-info/RECORD
