Metadata-Version: 2.3
Name: promptsite
Version: 0.4.0
Summary: PromptSite is a lightweight prompt lifecycle management package that helps you version control, track, experiment and debug with your LLM prompts with ease.
Author: Dakuang
Author-email: dakuang1980@gmail.com
Requires-Python: >=3.9,<4.0
Classifier: Programming Language :: Python :: 3
Classifier: Programming Language :: Python :: 3.9
Classifier: Programming Language :: Python :: 3.10
Classifier: Programming Language :: Python :: 3.11
Classifier: Programming Language :: Python :: 3.12
Classifier: Programming Language :: Python :: 3.13
Requires-Dist: click (>=8.1.7,<9.0.0)
Requires-Dist: datamodel-code-generator (>=0.26.0,<0.27.0)
Requires-Dist: gitpython (>=3.1.40,<4.0.0)
Requires-Dist: pandas (>=2.1.0,<3.0.0)
Requires-Dist: pydantic (>=2.10.0,<3.0.0)
Requires-Dist: pyyaml (>=6.0.1,<7.0.0)
